shift/barrel_left_shifter/BarrelLeftShifter.sv
// Barrel Left Shifter (shell)
//
// Synopsis:
//   Variable left shift implemented as a barrel shifter.

`timescale 1ns/1ps

module BarrelLeftShifter #(
	parameter int unsigned DATA_W  = 32,
	parameter int unsigned SHIFT_W = $clog2(DATA_W)
) (
	input  logic [DATA_W-1:0]  data_in,
	input  logic [SHIFT_W-1:0] shift_amount,
	output logic [DATA_W-1:0]  data_out
);

	logic [DATA_W-1:0] stage [SHIFT_W+1];

	assign stage[0] = data_in;

	for (genvar i = 0; i < SHIFT_W; i++) begin : gen_stage
		assign stage[i+1] = shift_amount[i] ? (stage[i] << (1 << i)) : stage[i];
	end

	assign data_out = stage[SHIFT_W];

endmodule

shift/barrel_left_shifter/BarrelLeftShifterTb.sv
`timescale 1ns/1ps

module BarrelLeftShifterTb;
	localparam int unsigned DATA_W  = 32;
	localparam int unsigned SHIFT_W = $clog2(DATA_W);

	logic [DATA_W-1:0]  data_in;
	logic [SHIFT_W-1:0] shift_amount;
	logic [DATA_W-1:0]  data_out;

	BarrelLeftShifter #(
		.DATA_W(DATA_W),
		.SHIFT_W(SHIFT_W)
	) dut (
		.data_in(data_in),
		.shift_amount(shift_amount),
		.data_out(data_out)
	);

	task automatic check(input logic [DATA_W-1:0] d, input logic [SHIFT_W-1:0] s);
		logic [DATA_W-1:0] exp;
		data_in = d;
		shift_amount = s;
		#1;
		exp = d << s;
		if (data_out !== exp) begin
			$display("ERROR BarrelLeftShifter: d=%h s=%0d exp=%h got=%h", d, s, exp, data_out);
			$fatal(1);
		end
	endtask

	initial begin
		$dumpfile("shift/barrel_left_shifter/BarrelLeftShifter.vcd");
		$dumpvars(0, BarrelLeftShifterTb);

		data_in = '0;
		shift_amount = '0;
		#1;

		check(32'h0000_0001, 5);
		check(32'h1234_5678, 8);
		check(32'hFFFF_FFFF, 31);

		for (int unsigned t = 0; t < 200; t++) begin
			check($urandom(), $urandom_range(DATA_W-1, 0));
		end

		$display("PASS: BarrelLeftShifterTb");
		$finish;
	end

endmodule

shift/barrel_left_shifter/BarrelLeftShifter.vcd
$date
	Wed Apr 15 11:11:25 2026
$end
$version
	Icarus Verilog
$end
$timescale
	1ps
$end
$scope module BarrelLeftShifterTb $end
$var wire 32 ! data_out [31:0] $end
$var parameter 32 " DATA_W $end
$var parameter 32 # SHIFT_W $end
$var reg 32 $ data_in [31:0] $end
$var reg 5 % shift_amount [4:0] $end
$scope module dut $end
$var wire 32 & data_in [31:0] $end
$var wire 32 ' data_out [31:0] $end
$var wire 5 ( shift_amount [4:0] $end
$var parameter 32 ) DATA_W $end
$var parameter 32 * SHIFT_W $end
$scope begin gen_stage[0] $end
$var parameter 2 + i $end
$upscope $end
$scope begin gen_stage[1] $end
$var parameter 2 , i $end
$upscope $end
$scope begin gen_stage[2] $end
$var parameter 3 - i $end
$upscope $end
$scope begin gen_stage[3] $end
$var parameter 3 . i $end
$upscope $end
$scope begin gen_stage[4] $end
$var parameter 4 / i $end
$upscope $end
$upscope $end
$scope begin $ivl_for_loop0 $end
$var reg 32 0 t [31:0] $end
$upscope $end
$scope task check $end
$upscope $end
$upscope $end
$enddefinitions $end
$comment Show the parameter values. $end
$dumpall
b100 /
b11 .
b10 -
b1 ,
b0 +
b101 *
b100000 )
b101 #
b100000 "
$end
#0
$dumpvars
b0 0
b0 (
b0 '
b0 &
b0 %
b0 $
b0 !
$end
#1000
b100000 !
b100000 '
b101 %
b101 (
b1 $
b1 &
#2000
b110100010101100111100000000000 !
b110100010101100111100000000000 '
b1000 %
b1000 (
b10010001101000101011001111000 $
b10010001101000101011001111000 &
#3000
b10000000000000000000000000000000 !
b10000000000000000000000000000000 '
b11111 %
b11111 (
b11111111111111111111111111111111 $
b11111111111111111111111111111111 &
#4000
b10101001101010010010000000000 !
b10101001101010010010000000000 '
b1000 %
b1000 (
b10010010000101010011010100100100 $
b10010010000101010011010100100100 &
#5000
b100001001101011000001001000000 !
b100001001101011000001001000000 '
b110 %
b110 (
b100100001001101011000001001 $
b100100001001101011000001001 &
b1 0
#6000
b1101000000000000000000000000 !
b1101000000000000000000000000 '
b11000 %
b11000 (
b10000110101110010111101100001101 $
b10000110101110010111101100001101 &
b10 0
#7000
b1100101100001010000100011001010 !
b1100101100001010000100011001010 '
b1 %
b1 (
b110010110000101000010001100101 $
b110010110000101000010001100101 &
b11 0
#8000
b11100011000000010000000000000000 !
b11100011000000010000000000000000 '
b10000 %
b10000 (
b10000000111100111110001100000001 $
b10000000111100111110001100000001 &
b100 0
#9000
b10001011101100000000000000000000 !
b10001011101100000000000000000000 '
b10011 %
b10011 (
b10111011001000111111000101110110 $
b10111011001000111111000101110110 &
b101 0
#10000
b11101101000000000000000000000000 !
b11101101000000000000000000000000 '
b11000 %
b11000 (
b11110110110101000101011111101101 $
b11110110110101000101011111101101 &
b110 0
#11000
b11011110100111111001000000000000 !
b11011110100111111001000000000000 '
b1100 %
b1100 (
b11111100111111011110100111111001 $
b11111100111111011110100111111001 &
b111 0
#12000
b11011110000100110001010000000000 !
b11011110000100110001010000000000 '
b1010 %
b1010 (
b1100010111101111000010011000101 $
b1100010111101111000010011000101 &
b1000 0
#13000
b1010111111110111111001010000000 !
b1010111111110111111001010000000 '
b111 %
b111 (
b11110010101011111111011111100101 $
b11110010101011111111011111100101 &
b1001 0
#14000
b10010000000000000000000000000 !
b10010000000000000000000000000 '
b11000 %
b11000 (
b1001001100101101011000010010 $
b1001001100101101011000010010 &
b1010 0
#15000
b110100111110010000000000000 !
b110100111110010000000000000 '
b1100 %
b1100 (
b11111001001100000110100111110010 $
b11111001001100000110100111110010 &
b1011 0
#16000
b111101011101000000000000000 !
b111101011101000000000000000 '
b1110100000000000111101011101000 $
b1110100000000000111101011101000 &
b1100 0
#17000
b11000010010010101110000000000000 !
b11000010010010101110000000000000 '
b1011 %
b1011 (
b10101110010110000100100101011100 $
b10101110010110000100100101011100 &
b1101 0
#18000
b10101010110101100000101101000000 !
b10101010110101100000101101000000 '
b110 %
b110 (
b10110101010110101100000101101 $
b10110101010110101100000101101 &
b1110 0
#19000
b1100010011000110000000000000000 !
b1100010011000110000000000000000 '
b10000 %
b10000 (
b110001111011110110001001100011 $
b110001111011110110001001100011 &
b1111 0
#20000
b10001010000000000000000000000000 !
b10001010000000000000000000000000 '
b10010 %
b10010 (
b1000000001110110010001010000000 $
b1000000001110110010001010000000 &
b10000 0
#21000
b11110000100010110101010000000000 !
b11110000100010110101010000000000 '
b1001 %
b1001 (
b11010101011110000100010110101010 $
b11010101011110000100010110101010 &
b10001 0
#22000
b10010110010000000111110100101100 !
b10010110010000000111110100101100 '
b1 %
b1 (
b1001011001000000011111010010110 $
b1001011001000000011111010010110 &
b10010 0
#23000
b11010111100001110000000110100000 !
b11010111100001110000000110100000 '
b101 %
b101 (
b110101111000011100000001101 $
b110101111000011100000001101 &
b10011 0
#24000
b11111011101011010110000000000000 !
b11111011101011010110000000000000 '
b1101 %
b1101 (
b10110101100111111101110101101011 $
b10110101100111111101110101101011 &
b10100 0
#25000
b1011101001010000000100000000000 !
b1011101001010000000100000000000 '
b1010 %
b1010 (
b1000101110100101000000010 $
b1000101110100101000000010 &
b10101 0
#26000
b11111110100100011101000000000000 !
b11111110100100011101000000000000 '
b1100 %
b1100 (
b10001110111111111110100100011101 $
b10001110111111111110100100011101 &
b10110 0
#27000
b1001001001000110000000000000000 !
b1001001001000110000000000000000 '
b10000 %
b10000 (
b10010001100001000100100100100011 $
b10010001100001000100100100100011 &
b10111 0
#28000
b101011100110000101011001010000 !
b101011100110000101011001010000 '
b11 %
b11 (
b1100101011100110000101011001010 $
b1100101011100110000101011001010 &
b11000 0
#29000
b11110010000000000000000000000000 !
b11110010000000000000000000000000 '
b11000 %
b11000 (
b11111001011010001011110111110010 $
b11111001011010001011110111110010 &
b11001 0
#30000
b10010110011010000010000000000000 !
b10010110011010000010000000000000 '
b1101 %
b1101 (
b10100000110001001011001101000001 $
b10100000110001001011001101000001 &
b11010 0
#31000
b100000111100110111100000000000 !
b100000111100110111100000000000 '
b1000 %
b1000 (
b10111100001000001111001101111000 $
b10111100001000001111001101111000 &
b11011 0
#32000
b1011000000000000000000000000000 !
b1011000000000000000000000000000 '
b11011 %
b11011 (
b11110101110001010000110111101011 $
b11110101110001010000110111101011 &
b11100 0
#33000
b11000000000000000000000000000 !
b11000000000000000000000000000 '
b11010 %
b11010 (
b11100011010010111111100111000110 $
b11100011010010111111100111000110 &
b11101 0
#34000
b1010111100000000000000000000 !
b1010111100000000000000000000 '
b10010 %
b10010 (
b1011110011101010000001010111100 $
b1011110011101010000001010111100 &
b11110 0
#35000
b11101011110011010000010110000000 !
b11101011110011010000010110000000 '
b111 %
b111 (
b101110101111001101000001011 $
b101110101111001101000001011 &
b11111 0
#36000
b11000010100000000000000000000 !
b11000010100000000000000000000 '
b10100 %
b10100 (
b11000010111100100100000110000101 $
b11000010111100100100000110000101 &
b100000 0
#37000
b1110110000000000000000000 !
b1110110000000000000000000 '
b10011 %
b10011 (
b11101110011000110000000111011 $
b11101110011000110000000111011 &
b100001 0
#38000
b1100100111111000000000000000000 !
b1100100111111000000000000000000 '
b10001 %
b10001 (
b111111001000110011001001111110 $
b111111001000110011001001111110 &
b100010 0
#39000
b100000000000000000000000000000 !
b100000000000000000000000000000 '
b11101 %
b11101 (
b11111000110110011001101111110001 $
b11111000110110011001101111110001 &
b100011 0
#40000
b1110110001000000000000000000000 !
b1110110001000000000000000000000 '
b10100 %
b10100 (
b10110001001000110000011101100010 $
b10110001001000110000011101100010 &
b100100 0
#41000
b10011111000000000000000000000000 !
b10011111000000000000000000000000 '
b11000 %
b11000 (
b11001111101000010101010110011111 $
b11001111101000010101010110011111 &
b100101 0
#42000
b1101101010011111100000000000000 !
b1101101010011111100000000000000 '
b1011 %
b1011 (
b11111100011011011010100111111000 $
b11111100011011011010100111111000 &
b100110 0
#43000
b11111000100010101101001111100000 !
b11111000100010101101001111100000 '
b101 %
b101 (
b1001111110001000101011010011111 $
b1001111110001000101011010011111 &
b100111 0
#44000
b1011011000000000000000000000000 !
b1011011000000000000000000000000 '
b11000 %
b11000 (
b101101110010111100000001011011 $
b101101110010111100000001011011 &
b101000 0
#45000
b11000110010010010010000000000000 !
b11000110010010010010000000000000 '
b1101 %
b1101 (
b100100101011100011001001001001 $
b100100101011100011001001001001 &
b101001 0
#46000
b1111111110110000001101011100000 !
b1111111110110000001101011100000 '
b101 %
b101 (
b1101011111111101100000011010111 $
b1101011111111101100000011010111 &
b101010 0
#47000
b101111100101100000000000000000 !
b101111100101100000000000000000 '
b10000 %
b10000 (
b11001011001000010010111110010110 $
b11001011001000010010111110010110 &
b101011 0
#48000
b100000000000000000000000000000 !
b100000000000000000000000000000 '
b11100 %
b11100 (
b1100001001011001100111011000010 $
b1100001001011001100111011000010 &
b101100 0
#49000
b11010011101110000000000000000000 !
b11010011101110000000000000000000 '
b10011 %
b10011 (
b111011100000100101101001110111 $
b111011100000100101101001110111 &
b101101 0
#50000
b10000110011011011000100100000000 !
b10000110011011011000100100000000 '
b111 %
b111 (
b10001001000011001101101100010010 $
b10001001000011001101101100010010 &
b101110 0
#51000
b1011011010000000000000000000 !
b1011011010000000000000000000 '
b10011 %
b10011 (
b10110110111001011000000101101101 $
b10110110111001011000000101101101 &
b101111 0
#52000
b1010001111000111110000000000000 !
b1010001111000111110000000000000 '
b1101 %
b1101 (
b10001111110100101000111100011111 $
b10001111110100101000111100011111 &
b110000 0
#53000
b1101100100101111100001010000000 !
b1101100100101111100001010000000 '
b111 %
b111 (
b11000010110110010010111110000101 $
b11000010110110010010111110000101 &
b110001 0
#54000
b10010101101100000000000000000000 !
b10010101101100000000000000000000 '
b10100 %
b10100 (
b10101101110110100101100101011011 $
b10101101110110100101100101011011 &
b110010 0
#55000
b10111000111111000000000000000000 !
b10111000111111000000000000000000 '
b10010 %
b10010 (
b11111111100101010111000111111 $
b11111111100101010111000111111 &
b110011 0
#56000
b10101011000110101100000000000 !
b10101011000110101100000000000 '
b1000 %
b1000 (
b10101100000101010110001101011000 $
b10101100000101010110001101011000 &
b110100 0
#57000
b110100000110010001110000000000 !
b110100000110010001110000000000 '
b1001 %
b1001 (
b1000111000110100000110010001110 $
b1000111000110100000110010001110 &
b110101 0
#58000
b11110100110101100110011111101000 !
b11110100110101100110011111101000 '
b10 %
b10 (
b11111101001101011001100111111010 $
b11111101001101011001100111111010 &
b110110 0
#59000
b1011000010111011100110000000000 !
b1011000010111011100110000000000 '
b1010 %
b1010 (
b10111001100101100001011101110011 $
b10111001100101100001011101110011 &
b110111 0
#60000
b11001101010000010111100000000000 !
b11001101010000010111100000000000 '
b1011 %
b1011 (
b10111100110011010100000101111 $
b10111100110011010100000101111 &
b111000 0
#61000
b1100101111100000000000000000000 !
b1100101111100000000000000000000 '
b10100 %
b10100 (
b101111110110000101011001011111 $
b101111110110000101011001011111 &
b111001 0
#62000
b10001111110111110111000000000000 !
b10001111110111110111000000000000 '
b1100 %
b1100 (
b11111011111110001111110111110111 $
b11111011111110001111110111110111 &
b111010 0
#63000
b1011100110000000000000000000000 !
b1011100110000000000000000000000 '
b10101 %
b10101 (
b1110011000010010001101011100110 $
b1110011000010010001101011100110 &
b111011 0
#64000
b11110000010010100100000000000000 !
b11110000010010100100000000000000 '
b1110 %
b1110 (
b10010100110011111100000100101001 $
b10010100110011111100000100101001 &
b111100 0
#65000
b1010100110110110011011010000000 !
b1010100110110110011011010000000 '
b110 %
b110 (
b1101101010100110110110011011010 $
b1101101010100110110110011011010 &
b111101 0
#66000
b1011100010101101010000000000000 !
b1011100010101101010000000000000 '
b1101 %
b1101 (
b1011010100010101110001010110101 $
b1011010100010101110001010110101 &
b111110 0
#67000
b10010111100100000000000000000000 !
b10010111100100000000000000000000 '
b10100 %
b10100 (
b10111100111100010001100101111001 $
b10111100111100010001100101111001 &
b111111 0
#68000
b110011010000000000000000000000 !
b110011010000000000000000000000 '
b10010 %
b10010 (
b1101000011101000000110011010000 $
b1101000011101000000110011010000 &
b1000000 0
#69000
b10101101101010110000000000000000 !
b10101101101010110000000000000000 '
b10000 %
b10000 (
b11010101111101101010110110101011 $
b11010101111101101010110110101011 &
b1000001 0
#70000
b10111011010110111011100000000000 !
b10111011010110111011100000000000 '
b1001 %
b1001 (
b11101110010111011010110111011100 $
b11101110010111011010110111011100 &
b1000010 0
#71000
b11110111001011111101000000000000 !
b11110111001011111101000000000000 '
b1100 %
b1100 (
b1111110110111110111001011111101 $
b1111110110111110111001011111101 &
b1000011 0
#72000
b11010101011000000000000000000000 !
b11010101011000000000000000000000 '
b10100 %
b10100 (
b10101011000011101110110101010110 $
b10101011000011101110110101010110 &
b1000100 0
#73000
b110011110110010111011001100111 !
b110011110110010111011001100111 '
b0 %
b0 (
b110011110110010111011001100111 $
b110011110110010111011001100111 &
b1000101 0
#74000
b11011011011111011100110110110000 !
b11011011011111011100110110110000 '
b11 %
b11 (
b11011011011011111011100110110110 $
b11011011011011111011100110110110 &
b1000110 0
#75000
b10001100001110111100100000000000 !
b10001100001110111100100000000000 '
b1011 %
b1011 (
b10111100110100011000011101111001 $
b10111100110100011000011101111001 &
b1000111 0
#76000
b101000000000000000000000000000 !
b101000000000000000000000000000 '
b11001 %
b11001 (
b11001010011101001011111110010100 $
b11001010011101001011111110010100 &
b1001000 0
#77000
b1000111111001011000000010000000 !
b1000111111001011000000010000000 '
b101 %
b101 (
b10001111110010110000000100 $
b10001111110010110000000100 &
b1001001 0
#78000
b11011100101101101001110110110000 !
b11011100101101101001110110110000 '
b100 %
b100 (
b11101101110010110110100111011011 $
b11101101110010110110100111011011 &
b1001010 0
#79000
b101100001011011111011001000000 !
b101100001011011111011001000000 '
b110 %
b110 (
b11101100101100001011011111011001 $
b11101100101100001011011111011001 &
b1001011 0
#80000
b1100000000000000000000000000000 !
b1100000000000000000000000000000 '
b11100 %
b11100 (
b111011010001011110001001110110 $
b111011010001011110001001110110 &
b1001100 0
#81000
b1101100000000000000000000000000 !
b1101100000000000000000000000000 '
b11001 %
b11001 (
b11011011000101110010110110110110 $
b11011011000101110010110110110110 &
b1001101 0
#82000
b11010010001100000000000000000 !
b11010010001100000000000000000 '
b10000 %
b10000 (
b100011000001110001101001000110 $
b100011000001110001101001000110 &
b1001110 0
#83000
b1111101110000000000000000000000 !
b1111101110000000000000000000000 '
b10110 %
b10110 (
b11111011110100100110000111110111 $
b11111011110100100110000111110111 &
b1001111 0
#84000
b10110100000000000000000000000000 !
b10110100000000000000000000000000 '
b11000 %
b11000 (
b1011010011011101011101010110100 $
b1011010011011101011101010110100 &
b1010000 0
#85000
b1010001111100110110010010100000 !
b1010001111100110110010010100000 '
b10 %
b10 (
b10010100011111001101100100101000 $
b10010100011111001101100100101000 &
b1010001 0
#86000
b10001111000101001100001100011100 !
b10001111000101001100001100011100 '
b1100011110001010011000011000111 $
b1100011110001010011000011000111 &
b1010010 0
#87000
b11001000000100000000000000000000 !
b11001000000100000000000000000000 '
b10001 %
b10001 (
b100011101111110010000001000 $
b100011101111110010000001000 &
b1010011 0
#88000
b10011011111101000000000000000000 !
b10011011111101000000000000000000 '
b10010 %
b10010 (
b1111110101001111010011011111101 $
b1111110101001111010011011111101 &
b1010100 0
#89000
b11100000000000000000000000000 !
b11100000000000000000000000000 '
b11000 %
b11000 (
b1110001101111001000000011100 $
b1110001101111001000000011100 &
b1010101 0
#90000
b1101001101000000100011011010000 !
b1101001101000000100011011010000 '
b11 %
b11 (
b1101101001101000000100011011010 $
b1101101001101000000100011011010 &
b1010110 0
#91000
b10100111010100111011001100000000 !
b10100111010100111011001100000000 '
b111 %
b111 (
b10110011010011101010011101100110 $
b10110011010011101010011101100110 &
b1010111 0
#92000
b10011000000000000000000000000000 !
b10011000000000000000000000000000 '
b11011 %
b11011 (
b111001111101010000010001110011 $
b111001111101010000010001110011 &
b1011000 0
#93000
b0 !
b0 '
b11111 %
b11111 (
b10101111001110101011001101011110 $
b10101111001110101011001101011110 &
b1011001 0
#94000
b11010101000111000000101110101010 !
b11010101000111000000101110101010 '
b1 %
b1 (
b11101010100011100000010111010101 $
b11101010100011100000010111010101 &
b1011010 0
#95000
b101110010000000000000000000 !
b101110010000000000000000000 '
b10011 %
b10011 (
b1011100111100000000000010111001 $
b1011100111100000000000010111001 &
b1011011 0
#96000
b1100000000000000000000000000000 !
b1100000000000000000000000000000 '
b11100 %
b11100 (
b11001011001001110011011110010110 $
b11001011001001110011011110010110 &
b1011100 0
#97000
b101100111110010011000000000000 !
b101100111110010011000000000000 '
b1011 %
b1011 (
b10010011001001011001111100100110 $
b10010011001001011001111100100110 &
b1011101 0
#98000
b10100000000000000000000000000000 !
b10100000000000000000000000000000 '
b11101 %
b11101 (
b10111110100110011000001101111101 $
b10111110100110011000001101111101 &
b1011110 0
#99000
b11000011000000000000000000000000 !
b11000011000000000000000000000000 '
b10111 %
b10111 (
b11000011011000010101011110000110 $
b11000011011000010101011110000110 &
b1011111 0
#100000
b1010011011011111100000000000000 !
b1010011011011111100000000000000 '
b1101 %
b1101 (
b10111111010110101001101101111110 $
b10111111010110101001101101111110 &
b1100000 0
#101000
b1100111100000000000000000000000 !
b1100111100000000000000000000000 '
b10111 %
b10111 (
b1100111110000111011011011001111 $
b1100111110000111011011011001111 &
b1100001 0
#102000
b1001010001110010011111010000000 !
b1001010001110010011111010000000 '
b110 %
b110 (
b1111101001010001110010011111010 $
b1111101001010001110010011111010 &
b1100010 0
#103000
b1010000001001000101110000000000 !
b1010000001001000101110000000000 '
b1010 %
b1010 (
b10001011100101000000100100010111 $
b10001011100101000000100100010111 &
b1100011 0
#104000
b1101110111100100011000011000000 !
b1101110111100100011000011000000 '
b101 %
b101 (
b11000011011101111001000110000110 $
b11000011011101111001000110000110 &
b1100100 0
#105000
b11010100011000101100111110101000 !
b11010100011000101100111110101000 '
b11 %
b11 (
b11111010100011000101100111110101 $
b11111010100011000101100111110101 &
b1100101 0
#106000
b10010000000000000000000000000000 !
b10010000000000000000000000000000 '
b11100 %
b11100 (
b10100100110101000101000101001 $
b10100100110101000101000101001 &
b1100110 0
#107000
b11001010111010011000101000000000 !
b11001010111010011000101000000000 '
b1001 %
b1001 (
b1100010111001010111010011000101 $
b1100010111001010111010011000101 &
b1100111 0
#108000
b11011001001111011010010110000000 !
b11011001001111011010010110000000 '
b111 %
b111 (
b10100101101100100111101101001011 $
b10100101101100100111101101001011 &
b1101000 0
#109000
b100010111001101110110000000000 !
b100010111001101110110000000000 '
b1000 %
b1000 (
b1110110001000101110011011101100 $
b1110110001000101110011011101100 &
b1101001 0
#110000
b1100011010001010011100000000000 !
b1100011010001010011100000000000 '
b1010 %
b1010 (
b10100111010110001101000101001110 $
b10100111010110001101000101001110 &
b1101010 0
#111000
b1111011111101101010010000000000 !
b1111011111101101010010000000000 '
b11010100100111101111110110101001 $
b11010100100111101111110110101001 &
b1101011 0
#112000
b11101110010000111000000000000000 !
b11101110010000111000000000000000 '
b1110 %
b1110 (
b10000111000010111011100100001110 $
b10000111000010111011100100001110 &
b1101100 0
#113000
b10011111000000000000000000 !
b10011111000000000000000000 '
b10010 %
b10010 (
b1001111110101101100000010011111 $
b1001111110101101100000010011111 &
b1101101 0
#114000
b1011010000111010010101000000000 !
b1011010000111010010101000000000 '
b1000 %
b1000 (
b10010101010110100001110100101010 $
b10010101010110100001110100101010 &
b1101110 0
#115000
b1111011101011111111110011110000 !
b1111011101011111111110011110000 '
b11 %
b11 (
b11001111011101011111111110011110 $
b11001111011101011111111110011110 &
b1101111 0
#116000
b10010000000000000000000000000000 !
b10010000000000000000000000000000 '
b11100 %
b11100 (
b111100110011111010100001111001 $
b111100110011111010100001111001 &
b1110000 0
#117000
b10001011100101000000000000000000 !
b10001011100101000000000000000000 '
b10001 %
b10001 (
b11100101001000110100010111001010 $
b11100101001000110100010111001010 &
b1110001 0
#118000
b1100100101101011000000000000 !
b1100100101101011000000000000 '
b1100 %
b1100 (
b10110101101000001100100101101011 $
b10110101101000001100100101101011 &
b1110010 0
#119000
b10110000000000000000000000000000 !
b10110000000000000000000000000000 '
b11011 %
b11011 (
b11011011000010111101110110110110 $
b11011011000010111101110110110110 &
b1110011 0
#120000
b100000000000000000000000000000 !
b100000000000000000000000000000 '
b11100010000101101010101111000100 $
b11100010000101101010101111000100 &
b1110100 0
#121000
b1111110100111001001000000000000 !
b1111110100111001001000000000000 '
b1011 %
b1011 (
b11001001001011111101001110010010 $
b11001001001011111101001110010010 &
b1110101 0
#122000
b10111011001110110111111100000000 !
b10111011001110110111111100000000 '
b1000 %
b1000 (
b10111111101110110011101101111111 $
b10111111101110110011101101111111 &
b1110110 0
#123000
b11111010111111010000000000000000 !
b11111010111111010000000000000000 '
b1111 %
b1111 (
b11111101011011011111010111111010 $
b11111101011011011111010111111010 &
b1110111 0
#124000
b101001000010011001000000000000 !
b101001000010011001000000000000 '
b1011 %
b1011 (
b10011001010001010010000100110010 $
b10011001010001010010000100110010 &
b1111000 0
#125000
b11110011011000010000000000000000 !
b11110011011000010000000000000000 '
b1110 %
b1110 (
b11000010010011111100110110000100 $
b11000010010011111100110110000100 &
b1111001 0
#126000
b101000000000000000000000000000 !
b101000000000000000000000000000 '
b11010 %
b11010 (
b11100101010000111100111111001010 $
b11100101010000111100111111001010 &
b1111010 0
#127000
b10100001000000000000000000000000 !
b10100001000000000000000000000000 '
b11000 %
b11000 (
b1010000100101011010100010100001 $
b1010000100101011010100010100001 &
b1111011 0
#128000
b1111101100010110110101011111011 !
b1111101100010110110101011111011 '
b0 %
b0 (
b1111101100010110110101011111011 $
b1111101100010110110101011111011 &
b1111100 0
#129000
b11110000000000000000000000000000 !
b11110000000000000000000000000000 '
b11100 %
b11100 (
b1110111100000101001000011101111 $
b1110111100000101001000011101111 &
b1111101 0
#130000
b10110000011100101001101100000000 !
b10110000011100101001101100000000 '
b111 %
b111 (
b10011011011000001110010100110110 $
b10011011011000001110010100110110 &
b1111110 0
#131000
b10100011110000000000000000000000 !
b10100011110000000000000000000000 '
b10110 %
b10110 (
b1000111111010000101011010001111 $
b1000111111010000101011010001111 &
b1111111 0
#132000
b10010111100111100010000000000000 !
b10010111100111100010000000000000 '
b1010 %
b1010 (
b11000100011001011110011110001000 $
b11000100011001011110011110001000 &
b10000000 0
#133000
b110110000000000000000000000000 !
b110110000000000000000000000000 '
b11001 %
b11001 (
b11001101111100111000000110011011 $
b11001101111100111000000110011011 &
b10000001 0
#134000
b1010001000100110111110010100000 !
b1010001000100110111110010100000 '
b10 %
b10 (
b10010100010001001101111100101000 $
b10010100010001001101111100101000 &
b10000010 0
#135000
b1110101111101001011000000000000 !
b1110101111101001011000000000000 '
b1100 %
b1100 (
b10100101101101110101111101001011 $
b10100101101101110101111101001011 &
b10000011 0
#136000
b11110110000111100000000000000000 !
b11110110000111100000000000000000 '
b10000 %
b10000 (
b1111000111001111011000011110 $
b1111000111001111011000011110 &
b10000100 0
#137000
b11111011110110000000000000000000 !
b11111011110110000000000000000000 '
b10001 %
b10001 (
b11110110011110011111110111101100 $
b11110110011110011111110111101100 &
b10000101 0
#138000
b10101110000110111101000100000000 !
b10101110000110111101000100000000 '
b1000 %
b1000 (
b11101000101011100001101111010001 $
b11101000101011100001101111010001 &
b10000110 0
#139000
b110000000010010001000001000 !
b110000000010010001000001000 '
b11 %
b11 (
b100000110000000010010001000001 $
b100000110000000010010001000001 &
b10000111 0
#140000
b111011000000000000000000000000 !
b111011000000000000000000000000 '
b10101 %
b10101 (
b11101100010001001111100111011000 $
b11101100010001001111100111011000 &
b10001000 0
#141000
b1100011001011000100101011000000 !
b1100011001011000100101011000000 '
b101 %
b101 (
b101011000110010110001001010110 $
b101011000110010110001001010110 &
b10001001 0
#142000
b1110001011001101111101011100010 !
b1110001011001101111101011100010 '
b0 %
b0 (
b1110001011001101111101011100010 $
b1110001011001101111101011100010 &
b10001010 0
#143000
b10000000011011100110000000000000 !
b10000000011011100110000000000000 '
b1101 %
b1101 (
b10111001101011000000001101110011 $
b10111001101011000000001101110011 &
b10001011 0
#144000
b11110010011010001001000000000000 !
b11110010011010001001000000000000 '
b1011 %
b1011 (
b10001001001111100100110100010010 $
b10001001001111100100110100010010 &
b10001100 0
#145000
b1000100100011100100000000000000 !
b1000100100011100100000000000000 '
b1110 %
b1110 (
b11100100000010001001000111001 $
b11100100000010001001000111001 &
b10001101 0
#146000
b1110010100001000000000000000000 !
b1110010100001000000000000000000 '
b10010 %
b10010 (
b1010000110001011101110010100001 $
b1010000110001011101110010100001 &
b10001110 0
#147000
b10000000000000000000000000000 !
b10000000000000000000000000000 '
b11100 %
b11100 (
b11000000100100000101110110000001 $
b11000000100100000101110110000001 &
b10001111 0
#148000
b10011100000000000000000000000000 !
b10011100000000000000000000000000 '
b11010 %
b11010 (
b10010011101101010101010100100111 $
b10010011101101010101010100100111 &
b10010000 0
#149000
b1111100011000110111000011111 !
b1111100011000110111000011111 '
b0 %
b0 (
b1111100011000110111000011111 $
b1111100011000110111000011111 &
b10010001 0
#150000
b1011010010001101011000000000000 !
b1011010010001101011000000000000 '
b1001 %
b1001 (
b10101100001011010010001101011000 $
b10101100001011010010001101011000 &
b10010010 0
#151000
b10100110111010010011000101000 !
b10100110111010010011000101000 '
b1 %
b1 (
b10001010011011101001001100010100 $
b10001010011011101001001100010100 &
b10010011 0
#152000
b10011100001001011000000000000 !
b10011100001001011000000000000 '
b1011 %
b1011 (
b1001011001000100111000010010110 $
b1001011001000100111000010010110 &
b10010100 0
#153000
b10110101010101010100000000000000 !
b10110101010101010100000000000000 '
b1110 %
b1110 (
b10101010110000101101010101010101 $
b10101010110000101101010101010101 &
b10010101 0
#154000
b10000000000000000000000000000000 !
b10000000000000000000000000000000 '
b11111 %
b11111 (
b10010101100010110010101100101011 $
b10010101100010110010101100101011 &
b10010110 0
#155000
b1011010110100000000111010110100 !
b1011010110100000000111010110100 '
b10 %
b10 (
b11010110101101000000001110101101 $
b11010110101101000000001110101101 &
b10010111 0
#156000
b100111111111100001000000000000 !
b100111111111100001000000000000 '
b1010 %
b1010 (
b11000010010010011111111110000100 $
b11000010010010011111111110000100 &
b10011000 0
#157000
b10111101001101110011100000000000 !
b10111101001101110011100000000000 '
b1011 %
b1011 (
b1110011110101111010011011100111 $
b1110011110101111010011011100111 &
b10011001 0
#158000
b100000000000000000000000000000 !
b100000000000000000000000000000 '
b11101 %
b11101 (
b100100110110100101011001001001 $
b100100110110100101011001001001 &
b10011010 0
#159000
b11111001001000000000000000000000 !
b11111001001000000000000000000000 '
b10101 %
b10101 (
b11100100101110100000111111001001 $
b11100100101110100000111111001001 &
b10011011 0
#160000
b1111010100001000000000000000000 !
b1111010100001000000000000000000 '
b10010 %
b10010 (
b1010000101111000101111010100001 $
b1010000101111000101111010100001 &
b10011100 0
#161000
b11010010101001000101111110100000 !
b11010010101001000101111110100000 '
b100 %
b100 (
b11111101001010100100010111111010 $
b11111101001010100100010111111010 &
b10011101 0
#162000
b11010000100000101100000110000000 !
b11010000100000101100000110000000 '
b111 %
b111 (
b11000001101000010000010110000011 $
b11000001101000010000010110000011 &
b10011110 0
#163000
b1010001110010000000000000000 !
b1010001110010000000000000000 '
b1111 %
b1111 (
b111001010001100001010001110010 $
b111001010001100001010001110010 &
b10011111 0
#164000
b10101011111001001101000000000 !
b10101011111001001101000000000 '
b110 %
b110 (
b110100010101011111001001101000 $
b110100010101011111001001101000 &
b10100000 0
#165000
b0 !
b0 '
b11111 %
b11111 (
b11000011010001100000110110000110 $
b11000011010001100000110110000110 &
b10100001 0
